django/chatbot/__init__.py
django/chatbot/admin.py
django/chatbot/apps.py
django/chatbot/chatbot.py
django/chatbot/handler.py
django/chatbot/models.py
django/chatbot/tests.py
django/chatbot/migrations/__init__.py
django/chatbot/views/__init__.py
django/chatbot/views/botframework.py
django_chatbot-0.0.2.3.dist-info/LICENSE
django_chatbot-0.0.2.3.dist-info/METADATA
django_chatbot-0.0.2.3.dist-info/WHEEL
django_chatbot-0.0.2.3.dist-info/top_level.txt
django_chatbot-0.0.2.3.dist-info/zip-safe
django_chatbot-0.0.2.3.dist-info/RECORD
